Metadata-Version: 2.1
Name: mashup-yt
Version: 0.0.2
Summary: This module creates a mashup of songs of your favorite singer with a single click.
Home-page: https://github.com/Chitru4/mashup_yt
Download-URL: https://github.com/Chitru4/mashup_yt/archive/refs/tags/mashup_yt.tar.gz
Author: Chitraksh Kumar
Author-email: chitraksh24@gmail.com
License: MIT
Keywords: MASHUP,YOUTUBE,PROJECT,MUSIC,MP3
Classifier: Development Status :: 3 - Alpha
Classifier: Intended Audience :: Developers
Classifier: Topic :: Software Development :: Build Tools
Classifier: License :: OSI Approved :: MIT License
Classifier: Programming Language :: Python :: 3
Classifier: Programming Language :: Python :: 3.4
Classifier: Programming Language :: Python :: 3.5
Classifier: Programming Language :: Python :: 3.6
License-File: LICENSE
